smtpc/__init__.py
smtpc/cli.py
smtpc/config.py
smtpc/defaults.py
smtpc/encryption.py
smtpc/enums.py
smtpc/errors.py
smtpc/message.py
smtpc/predefined_messages.py
smtpc/predefined_profiles.py
smtpc/utils.py
tests/__init__.py
tests/test_config.py
tests/test_message_builder.py
tests/test_templates.py
tests/test_utils.py
tests/e2e/__init__.py
tests/e2e/conftest.py
tests/e2e/test_initial.py
tests/e2e/test_messages_add.py
tests/e2e/test_messages_delete.py
tests/e2e/test_messages_list.py
tests/e2e/test_profiles_add.py
tests/e2e/test_profiles_delete.py
tests/e2e/test_profiles_list.py
tests/e2e/test_send.py
smtpc-0.9.2.dist-info/LICENSE
smtpc-0.9.2.dist-info/METADATA
smtpc-0.9.2.dist-info/WHEEL
smtpc-0.9.2.dist-info/entry_points.txt
smtpc-0.9.2.dist-info/top_level.txt
smtpc-0.9.2.dist-info/RECORD
