Metadata-Version: 2.1
Name: smtpc
Version: 0.9.2
Summary: UNKNOWN
Home-page: https://github.com/msztolcman/smtpc
Author: Marcin Sztolcman
Author-email: marcin@urzenia.net
License: MIT
Download-URL: https://github.com/msztolcman/smtpc
Project-URL: GitHub: issues, https://github.com/msztolcman/smtpc/issues
Project-URL: GitHub: repo, https://github.com/msztolcman/smtpc
Platform: UNKNOWN
Classifier: Development Status :: 4 - Beta
Classifier: Environment :: Console
Classifier: Intended Audience :: Developers
Classifier: Intended Audience :: System Administrators
Classifier: License :: OSI Approved :: MIT License
Classifier: Operating System :: POSIX
Classifier: Operating System :: MacOS :: MacOS X
Classifier: Programming Language :: Python
Classifier: Programming Language :: Python :: 3
Classifier: Programming Language :: Python :: 3 :: Only
Classifier: Programming Language :: Python :: 3.7
Classifier: Programming Language :: Python :: 3.8
Classifier: Programming Language :: Python :: 3.9
Classifier: Programming Language :: Python :: 3.10
Classifier: Topic :: Communications
Classifier: Topic :: Communications :: Email
Classifier: Topic :: Communications :: Email :: Email Clients (MUA)
Classifier: Topic :: Utilities
Classifier: Topic :: Software Development
Classifier: Topic :: System :: Systems Administration
Requires-Python: >=3.7
Requires-Dist: structlog
Requires-Dist: fileperms
Requires-Dist: toml
Provides-Extra: extended
Requires-Dist: Jinja2 ; extra == 'extended'
Requires-Dist: colorama ; extra == 'extended'
Provides-Extra: secure
Requires-Dist: cryptography ; extra == 'secure'
